momentum_sdk/__init__.py
momentum_sdk/config.py
momentum_sdk/core.py
momentum_sdk/exceptions.py
momentum_sdk/py.typed
momentum_sdk/telemetry.py
momentum_sdk/lib/libmomentum_engine.dylib
momentum_sdk_test-0.1.6.dist-info/METADATA
momentum_sdk_test-0.1.6.dist-info/WHEEL
momentum_sdk_test-0.1.6.dist-info/RECORD
