Metadata-Version: 2.4
Name: momentum-sdk-test
Version: 0.1.6
Summary: Local prompt compression engine SDK
Requires-Python: >=3.9
Requires-Dist: cffi>=1.15.0
Requires-Dist: pydantic-settings>=2.0.0
Requires-Dist: pydantic>=2.0.0
Provides-Extra: dev
Requires-Dist: black>=23.0.0; extra == 'dev'
Requires-Dist: mypy>=1.0.0; extra == 'dev'
Requires-Dist: pytest-asyncio>=0.21.0; extra == 'dev'
Requires-Dist: pytest-cov>=4.0.0; extra == 'dev'
Requires-Dist: pytest>=7.0.0; extra == 'dev'
Requires-Dist: ruff>=0.0.200; extra == 'dev'
Requires-Dist: types-cffi>=1.15.0; extra == 'dev'
Requires-Dist: types-pyyaml>=6.0.0; extra == 'dev'
